<!--
CMS combination of the H -> gammagamma, ZZ, WW, tautau, bb, mumu and Zgamma decay modes for up to 138/fb.
Best-fit values and uncertainties taken from Figure B6, 
http://cms-results.web.cern.ch/cms-results/public-results/publications/HIG-22-001/
correlations from 10.17182/hepdata.127765.v1/t20
https://doi.org/10.17182/hepdata.127765
validated: waiting  
-->

<expmu dim="30" type="vn">
    <experiment>CMS</experiment>
    <source type="preliminary">HIG-22-001</source>
    <sqrts>13</sqrts>
    <mass>125.38</mass>
    <CL>68%</CL> <!-- optional -->
    

    <eff axis="d1" prod="ggH" decay="gammagamma">1.0</eff>
    <eff axis="d2" prod="VBF" decay="gammagamma">1.0</eff>
    <eff axis="d3" prod="WH" decay="gammagamma">1.0</eff>
    <eff axis="d4" prod="ZH" decay="gammagamma">1.0</eff>
    <eff axis="d5" prod="top" decay="gammagamma">1.0</eff>

    <eff axis="d6" prod="ggH" decay="ZZ">1.0</eff>
    <eff axis="d7" prod="VBF" decay="ZZ">1.0</eff>
    <eff axis="d8" prod="WH" decay="ZZ">1.0</eff>
    <eff axis="d9" prod="ZH" decay="ZZ">1.0</eff>
    <eff axis="d10" prod="top" decay="ZZ">1.0</eff>

    <eff axis="d11" prod="ggH" decay="WW">1.0</eff>
    <eff axis="d12" prod="VBF" decay="WW">1.0</eff>
    <eff axis="d13" prod="WH" decay="WW">1.0</eff>
    <eff axis="d14" prod="ZH" decay="WW">1.0</eff>
    <eff axis="d15" prod="top" decay="WW">1.0</eff>

    <eff axis="d16" prod="ggH" decay="tautau">1.0</eff>
    <eff axis="d17" prod="VBF" decay="tautau">1.0</eff>
    <eff axis="d18" prod="WH" decay="tautau">1.0</eff>
    <eff axis="d19" prod="ZH" decay="tautau">1.0</eff>
    <eff axis="d20" prod="top" decay="tautau">1.0</eff>

    <eff axis="d21" prod="ggH" decay="bb">1.0</eff>
    <eff axis="d22" prod="WH" decay="bb">1.0</eff>
    <eff axis="d23" prod="ZH" decay="bb">1.0</eff>
    <eff axis="d24" prod="top" decay="bb">1.0</eff>

    <eff axis="d25" prod="ggH" decay="mumu">1.0</eff>
    <eff axis="d26" prod="VBF" decay="mumu">1.0</eff>
    <eff axis="d27" prod="VH" decay="mumu">1.0</eff>
    <eff axis="d28" prod="top" decay="mumu">1.0</eff>

    <eff axis="d29" prod="ggH" decay="Zgamma">1.0</eff>
    <eff axis="d30" prod="VBF" decay="Zgamma">1.0</eff>

    <bestfit>
        <d1>1.08</d1>
        <d2>1.00</d2>
	<d3>1.43</d3>
        <d4>1.19</d4>
	<d5>1.38</d5>
        <d6>0.93</d6>
        <d7>0.32</d7>
        <d8>0.00</d8>        
        <d9>12.24</d9>        
	<d10>0.00</d10>
        <d11>0.90</d11>
        <d12>0.73</d12>
        <d13>2.41</d13>
        <d14>1.76</d14>
        <d15>1.44</d15>
        <d16>0.66</d16>
        <d17>0.86</d17>
        <d18>1.33</d18>
        <d19>1.89</d19>
        <d20>0.35</d20>
        <d21>5.31</d21>
        <d22>1.26</d22>
        <d23>0.90</d23>
        <d24>0.90</d24>
        <d25>0.33</d25>
        <d26>1.55</d26>
        <d27>5.63</d27>
        <d28>3.07</d28>
        <d29>3.86</d29>
        <d30>-4.43</d30>
    </bestfit>

    <param>
        <uncertainty axis="d1" side="left">-0.11</uncertainty>
        <uncertainty axis="d1" side="right">+0.12</uncertainty>
        <uncertainty axis="d2" side="left">-0.32</uncertainty>
        <uncertainty axis="d2" side="right">+0.35</uncertainty>
        <uncertainty axis="d3" side="left">-0.47</uncertainty>
        <uncertainty axis="d3" side="right">+0.54</uncertainty>
        <uncertainty axis="d4" side="left">-0.62</uncertainty>
        <uncertainty axis="d4" side="right">+0.71</uncertainty>
        <uncertainty axis="d5" side="left">-0.29</uncertainty>
        <uncertainty axis="d5" side="right">+0.34</uncertainty>
        <uncertainty axis="d6" side="left">-0.13</uncertainty>
        <uncertainty axis="d6" side="right">+0.14</uncertainty>
        <uncertainty axis="d7" side="left">-0.32</uncertainty>
        <uncertainty axis="d7" side="right">+0.48</uncertainty>
        <uncertainty axis="d8" side="left">-0.01</uncertainty>
        <uncertainty axis="d8" side="right">+1.55</uncertainty>
        <uncertainty axis="d9" side="left">-5.69</uncertainty>
        <uncertainty axis="d9" side="right">+6.59</uncertainty>
        <uncertainty axis="d10" side="left">-0.01</uncertainty>
        <uncertainty axis="d10" side="right">+0.73</uncertainty>
        <uncertainty axis="d11" side="left">-0.10</uncertainty>
        <uncertainty axis="d11" side="right">+0.11</uncertainty>
        <uncertainty axis="d12" side="left">-0.24</uncertainty>
        <uncertainty axis="d12" side="right">+0.28</uncertainty>
        <uncertainty axis="d13" side="left">-0.70</uncertainty>
        <uncertainty axis="d13" side="right">+0.72</uncertainty>
        <uncertainty axis="d14" side="left">-0.67</uncertainty>
        <uncertainty axis="d14" side="right">+0.75</uncertainty>
        <uncertainty axis="d15" side="left">-0.32</uncertainty>
        <uncertainty axis="d15" side="right">+0.32</uncertainty>
        <uncertainty axis="d16" side="left">-0.21</uncertainty>
        <uncertainty axis="d16" side="right">+0.21</uncertainty>
        <uncertainty axis="d17" side="left">-0.16</uncertainty>
        <uncertainty axis="d17" side="right">+0.17</uncertainty>
        <uncertainty axis="d18" side="left">-0.57</uncertainty>
        <uncertainty axis="d18" side="right">+0.61</uncertainty>
        <uncertainty axis="d19" side="left">-0.56</uncertainty>
        <uncertainty axis="d19" side="right">+0.65</uncertainty>
        <uncertainty axis="d20" side="left">-0.37</uncertainty>
        <uncertainty axis="d20" side="right">+0.44</uncertainty>
        <uncertainty axis="d21" side="left">-2.54</uncertainty>
        <uncertainty axis="d21" side="right">+2.97</uncertainty>
        <uncertainty axis="d22" side="left">-0.41</uncertainty>
        <uncertainty axis="d22" side="right">+0.42</uncertainty>
        <uncertainty axis="d23" side="left">-0.34</uncertainty>
        <uncertainty axis="d23" side="right">+0.36</uncertainty>	
        <uncertainty axis="d24" side="left">-0.44</uncertainty>
        <uncertainty axis="d24" side="right">+0.46</uncertainty> 
        <uncertainty axis="d25" side="left">-0.70</uncertainty>
        <uncertainty axis="d25" side="right">+0.74</uncertainty>
        <uncertainty axis="d26" side="left">-0.73</uncertainty>
        <uncertainty axis="d26" side="right">+0.86</uncertainty>
        <uncertainty axis="d27" side="left">-3.36</uncertainty>
        <uncertainty axis="d27" side="right">+3.04</uncertainty>
        <uncertainty axis="d28" side="left">-2.21</uncertainty>
        <uncertainty axis="d28" side="right">+2.63</uncertainty>                
        <uncertainty axis="d29" side="left">-1.23</uncertainty>
        <uncertainty axis="d29" side="right">+1.39</uncertainty> 
        <uncertainty axis="d30" side="left">-2.89</uncertainty>
        <uncertainty axis="d30" side="right">+3.82</uncertainty>     

        <correlation entry="d1d2">-0.2</correlation>
        <correlation entry="d1d3">-0.04</correlation>
        <correlation entry="d1d4">-0.02</correlation>
        <correlation entry="d1d5">0.03</correlation>
        <correlation entry="d1d6">0.17</correlation>
        <correlation entry="d1d7">0.02</correlation>
        <correlation entry="d1d8">0.01</correlation>
        <correlation entry="d1d9">0.01</correlation>
        <correlation entry="d1d10">0</correlation>
        <correlation entry="d1d11">0.23</correlation>
        <correlation entry="d1d12">0.02</correlation>
        <correlation entry="d1d13">0.02</correlation>
        <correlation entry="d1d14">0.01</correlation>
        <correlation entry="d1d15">0.01</correlation>
        <correlation entry="d1d16">0.10</correlation>
        <correlation entry="d1d17">0.01</correlation>
        <correlation entry="d1d18">0.02</correlation>
        <correlation entry="d1d19">0.02</correlation>
        <correlation entry="d1d20">0</correlation>
        <correlation entry="d1d21">0</correlation>
        <correlation entry="d1d22">0</correlation>
        <correlation entry="d1d23">0</correlation>
        <correlation entry="d1d24">0</correlation>
        <correlation entry="d1d25">0.01</correlation>
        <correlation entry="d1d26">0.01</correlation>
        <correlation entry="d1d27">0.01</correlation>
        <correlation entry="d1d28">0</correlation>
        <correlation entry="d1d29">0.07</correlation>
        <correlation entry="d1d30">0</correlation>
        
        <correlation entry="d2d3">0.03</correlation>
        <correlation entry="d2d4">0.01</correlation>
        <correlation entry="d2d5">0</correlation>
        <correlation entry="d2d6">0.02</correlation>
        <correlation entry="d2d7">0.03</correlation>
        <correlation entry="d2d8">0.01</correlation>
        <correlation entry="d2d9">0.01</correlation>
        <correlation entry="d2d10">0</correlation>
        <correlation entry="d2d11">0.01</correlation>
        <correlation entry="d2d12">0.01</correlation>
        <correlation entry="d2d13">0.01</correlation>
        <correlation entry="d2d14">0.01</correlation>
        <correlation entry="d2d15">0</correlation>
        <correlation entry="d2d16">0.04</correlation>
        <correlation entry="d2d17">0.02</correlation>
        <correlation entry="d2d18">0.02</correlation>
        <correlation entry="d2d19">0.02</correlation>
        <correlation entry="d2d20">0</correlation>
        <correlation entry="d2d21">0</correlation>
        <correlation entry="d2d22">0</correlation>
        <correlation entry="d2d23">0</correlation>
        <correlation entry="d2d24">0</correlation>
        <correlation entry="d2d25">0</correlation>
        <correlation entry="d2d26">0</correlation>
        <correlation entry="d2d27">0</correlation>
        <correlation entry="d2d28">0</correlation>        
        <correlation entry="d2d29">0.01</correlation>
        <correlation entry="d2d30">-0.01</correlation>
        
        <correlation entry="d3d4">-0.25</correlation>
        <correlation entry="d3d5">-0.04</correlation>
        <correlation entry="d3d6">0.01</correlation>
        <correlation entry="d3d7">0.01</correlation>
        <correlation entry="d3d8">0</correlation>
        <correlation entry="d3d9">0</correlation>
        <correlation entry="d3d10">0</correlation>
        <correlation entry="d3d11">0.01</correlation>
        <correlation entry="d3d12">0.01</correlation>
        <correlation entry="d3d13">0</correlation>
        <correlation entry="d3d14">0</correlation>
        <correlation entry="d3d15">0</correlation>
        <correlation entry="d3d16">0.01</correlation>
        <correlation entry="d3d17">0.01</correlation>
        <correlation entry="d3d18">0.01</correlation>
        <correlation entry="d3d19">0.01</correlation>
        <correlation entry="d3d20">0</correlation>
        <correlation entry="d3d21">0</correlation>
        <correlation entry="d3d22">0</correlation>
        <correlation entry="d3d23">0</correlation>
        <correlation entry="d3d24">0</correlation>
        <correlation entry="d3d25">0</correlation>
        <correlation entry="d3d26">0</correlation>
        <correlation entry="d3d27">0</correlation>
        <correlation entry="d3d28">0</correlation>                
        <correlation entry="d3d29">0</correlation>
        <correlation entry="d3d30">0</correlation>
        
        <correlation entry="d4d5">-0.04</correlation>
        <correlation entry="d4d6">0.01</correlation>
        <correlation entry="d4d7">0.01</correlation>
        <correlation entry="d4d8">0</correlation>
        <correlation entry="d4d9">0</correlation>
        <correlation entry="d4d10">0</correlation>
        <correlation entry="d4d11">0.01</correlation>
        <correlation entry="d4d12">0</correlation>
        <correlation entry="d4d13">0</correlation>
        <correlation entry="d4d14">0</correlation>
        <correlation entry="d4d15">0</correlation>
        <correlation entry="d4d16">0.01</correlation>
        <correlation entry="d4d17">0.01</correlation>
        <correlation entry="d4d18">0.01</correlation>
        <correlation entry="d4d19">0.03</correlation>
        <correlation entry="d4d20">0</correlation>
        <correlation entry="d4d21">0</correlation>
        <correlation entry="d4d22">0</correlation>
        <correlation entry="d4d23">0</correlation>
        <correlation entry="d4d24">0</correlation>
        <correlation entry="d4d25">0</correlation>
        <correlation entry="d4d26">0</correlation>
        <correlation entry="d4d27">0</correlation>
        <correlation entry="d4d28">0</correlation>        
        <correlation entry="d4d29">0</correlation>
        <correlation entry="d4d30">0</correlation>
        
        <correlation entry="d5d6">0.01</correlation>
        <correlation entry="d5d7">0</correlation>
        <correlation entry="d5d8">0</correlation>
        <correlation entry="d5d9">0</correlation>
        <correlation entry="d5d10">0</correlation>
        <correlation entry="d5d11">0.01</correlation>
        <correlation entry="d5d12">0</correlation>
        <correlation entry="d5d13">0.01</correlation>
        <correlation entry="d5d14">0</correlation>
        <correlation entry="d5d15">0.01</correlation>
        <correlation entry="d5d16">0.01</correlation>
        <correlation entry="d5d17">0.01</correlation>
        <correlation entry="d5d18">0.01</correlation>
        <correlation entry="d5d19">0.01</correlation>
        <correlation entry="d5d20">0.07</correlation>
        <correlation entry="d5d21">0</correlation>
        <correlation entry="d5d22">0</correlation>
        <correlation entry="d5d23">0</correlation>
        <correlation entry="d5d24">0.08</correlation>
        <correlation entry="d5d25">0</correlation>
        <correlation entry="d5d26">0</correlation>
        <correlation entry="d5d27">0</correlation>
        <correlation entry="d5d28">0.06</correlation>           
        <correlation entry="d5d29">0</correlation>
        <correlation entry="d5d30">0</correlation>
        
        <correlation entry="d6d7">-0.25</correlation>
        <correlation entry="d6d8">-0.04</correlation>
        <correlation entry="d6d9">-0.24</correlation>
        <correlation entry="d6d10">0.08</correlation>
        <correlation entry="d6d11">0.13</correlation>
        <correlation entry="d6d12">0.01</correlation>
        <correlation entry="d6d13">0.01</correlation>
        <correlation entry="d6d14">0.01</correlation>
        <correlation entry="d6d15">-0.02</correlation>
        <correlation entry="d6d16">0.05</correlation>
        <correlation entry="d6d17">0.02</correlation>
        <correlation entry="d6d18">0.01</correlation>
        <correlation entry="d6d19">0.01</correlation>
        <correlation entry="d6d20">0</correlation>
        <correlation entry="d6d21">0</correlation>
        <correlation entry="d6d22">0</correlation>
        <correlation entry="d6d23">0</correlation>
        <correlation entry="d6d24">0</correlation>
        <correlation entry="d6d25">0.01</correlation>
        <correlation entry="d6d26">0</correlation>
        <correlation entry="d6d27">0</correlation>
        <correlation entry="d6d28">0</correlation>        
        <correlation entry="d6d29">0.03</correlation>
        <correlation entry="d6d30">0</correlation>
        
        <correlation entry="d7d8">-0.07</correlation>
        <correlation entry="d7d9">0.12</correlation>
        <correlation entry="d7d10">-0.11</correlation>
        <correlation entry="d7d11">0</correlation>
        <correlation entry="d7d12">0.01</correlation>
        <correlation entry="d7d13">0.01</correlation>
        <correlation entry="d7d14">0</correlation>
        <correlation entry="d7d15">0.02</correlation>
        <correlation entry="d7d16">0.01</correlation>
        <correlation entry="d7d17">0.02</correlation>
        <correlation entry="d7d18">0.01</correlation>
        <correlation entry="d7d19">0</correlation>
        <correlation entry="d7d20">0</correlation>
        <correlation entry="d7d21">0</correlation>
        <correlation entry="d7d22">0</correlation>
        <correlation entry="d7d23">0</correlation>
        <correlation entry="d7d24">0</correlation>
        <correlation entry="d7d25">0</correlation>
        <correlation entry="d7d26">0</correlation>
        <correlation entry="d7d27">0</correlation>
        <correlation entry="d7d28">0</correlation>
        <correlation entry="d7d29">0</correlation>
        <correlation entry="d7d30">0</correlation>
        
        <correlation entry="d8d9">-0.63</correlation>
        <correlation entry="d8d10">0.22</correlation>
        <correlation entry="d8d11">0.01</correlation>
        <correlation entry="d8d12">0</correlation>
        <correlation entry="d8d13">-0.03</correlation>
        <correlation entry="d8d14">-0.01</correlation>
        <correlation entry="d8d15">-0.04</correlation>
        <correlation entry="d8d16">0.01</correlation>
        <correlation entry="d8d17">0</correlation>
        <correlation entry="d8d18">0</correlation>
        <correlation entry="d8d19">0.01</correlation>
        <correlation entry="d8d20">0.01</correlation>
        <correlation entry="d8d21">0</correlation>
        <correlation entry="d8d22">0</correlation>
        <correlation entry="d8d23">0</correlation>
        <correlation entry="d8d24">0</correlation>
        <correlation entry="d8d25">0</correlation>
        <correlation entry="d8d26">0</correlation>
        <correlation entry="d8d27">0</correlation>
        <correlation entry="d8d28">0</correlation>                
        <correlation entry="d8d29">0</correlation>
        <correlation entry="d8d30">0</correlation>
        
        <correlation entry="d9d10">-0.36</correlation>
        <correlation entry="d9d11">0</correlation>
        <correlation entry="d9d12">0</correlation>
        <correlation entry="d9d13">0.03</correlation>
        <correlation entry="d9d14">0</correlation>
        <correlation entry="d9d15">0.08</correlation>
        <correlation entry="d9d16">0.01</correlation>
        <correlation entry="d9d17">0.01</correlation>
        <correlation entry="d9d18">0.01</correlation>
        <correlation entry="d9d19">0</correlation>
        <correlation entry="d9d20">-0.01</correlation>
        <correlation entry="d9d21">-0.01</correlation>
        <correlation entry="d9d22">0</correlation>
        <correlation entry="d9d23">0</correlation>
        <correlation entry="d9d24">0.01</correlation>
        <correlation entry="d9d25">0</correlation>
        <correlation entry="d9d26">0</correlation>
        <correlation entry="d9d27">0</correlation>
        <correlation entry="d9d28">0.01</correlation>        
        <correlation entry="d9d29">0</correlation>
        <correlation entry="d9d30">0</correlation>
        
        <correlation entry="d10d11">0</correlation>
        <correlation entry="d10d12">0</correlation>
        <correlation entry="d10d13">-0.01</correlation>
        <correlation entry="d10d14">0</correlation>
        <correlation entry="d10d15">-0.15</correlation>
        <correlation entry="d10d16">0</correlation>
        <correlation entry="d10d17">0</correlation>
        <correlation entry="d10d18">0</correlation>
        <correlation entry="d10d19">0</correlation>
        <correlation entry="d10d20">0.02</correlation>
        <correlation entry="d10d21">0</correlation>
        <correlation entry="d10d22">0</correlation>
        <correlation entry="d10d23">0</correlation>
        <correlation entry="d10d24">-0.01</correlation>
        <correlation entry="d10d25">0</correlation>
        <correlation entry="d10d26">0</correlation>
        <correlation entry="d10d27">0</correlation>
        <correlation entry="d10d28">0</correlation>     
        <correlation entry="d10d29">0</correlation>
        <correlation entry="d10d30">0</correlation>
        
        <correlation entry="d11d12">-0.11</correlation>
        <correlation entry="d11d13">-0.04</correlation>
        <correlation entry="d11d14">0.02</correlation>
        <correlation entry="d11d15">0</correlation>
        <correlation entry="d11d16">0.1</correlation>
        <correlation entry="d11d17">0.01</correlation>
        <correlation entry="d11d18">0.02</correlation>
        <correlation entry="d11d19">0.05</correlation>
        <correlation entry="d11d20">0</correlation>
        <correlation entry="d11d21">0</correlation>
        <correlation entry="d11d22">0</correlation>
        <correlation entry="d11d23">0.01</correlation>
        <correlation entry="d11d24">0</correlation>
        <correlation entry="d11d25">0.01</correlation>
        <correlation entry="d11d26">0.01</correlation>
        <correlation entry="d11d27">0.01</correlation>
        <correlation entry="d11d28">0</correlation>
        <correlation entry="d11d29">0.08</correlation>
        <correlation entry="d11d30">0</correlation>
        
        <correlation entry="d12d13">0</correlation>
        <correlation entry="d12d14">0</correlation>
        <correlation entry="d12d15">0</correlation>
        <correlation entry="d12d16">0</correlation>
        <correlation entry="d12d17">-0.03</correlation>
        <correlation entry="d12d18">0.01</correlation>
        <correlation entry="d12d19">0</correlation>
        <correlation entry="d12d20">0</correlation>
        <correlation entry="d12d21">0</correlation>
        <correlation entry="d12d22">0</correlation>
        <correlation entry="d12d23">0</correlation>
        <correlation entry="d12d24">0</correlation>
        <correlation entry="d12d25">0</correlation>
        <correlation entry="d12d26">0</correlation>
        <correlation entry="d12d27">0</correlation>
        <correlation entry="d12d28">0</correlation>        
        <correlation entry="d12d29">0</correlation>
        <correlation entry="d12d30">0</correlation>
        
        <correlation entry="d13d14">-0.04</correlation>
        <correlation entry="d13d15">0.02</correlation>
        <correlation entry="d13d16">0.02</correlation>
        <correlation entry="d13d17">0.02</correlation>
        <correlation entry="d13d18">-0.08</correlation>
        <correlation entry="d13d19">0.01</correlation>
        <correlation entry="d13d20">0</correlation>
        <correlation entry="d13d21">0</correlation>
        <correlation entry="d13d22">0.01</correlation>
        <correlation entry="d13d23">0</correlation>
        <correlation entry="d13d24">0</correlation>
        <correlation entry="d13d25">0</correlation>
        <correlation entry="d13d26">0.01</correlation>
        <correlation entry="d13d27">0</correlation>
        <correlation entry="d13d28">0</correlation>                
        <correlation entry="d13d29">0</correlation>
        <correlation entry="d13d30">0</correlation>
        
        <correlation entry="d14d15">0.01</correlation>
        <correlation entry="d14d16">0.01</correlation>
        <correlation entry="d14d17">0.01</correlation>
        <correlation entry="d14d18">-0.01</correlation>
        <correlation entry="d14d19">-0.07</correlation>
        <correlation entry="d14d20">0.01</correlation>
        <correlation entry="d14d21">0</correlation>
        <correlation entry="d14d22">0</correlation>
        <correlation entry="d14d23">0.01</correlation>
        <correlation entry="d14d24">0</correlation>
        <correlation entry="d14d25">0</correlation>
        <correlation entry="d14d26">0</correlation>
        <correlation entry="d14d27">0</correlation>
        <correlation entry="d14d28">0</correlation>        
        <correlation entry="d14d29">0</correlation>
        <correlation entry="d14d30">0</correlation>
        
        <correlation entry="d15d16">0</correlation>
        <correlation entry="d15d17">0</correlation>
        <correlation entry="d15d18">0.01</correlation>
        <correlation entry="d15d19">0</correlation>
        <correlation entry="d15d20">-0.22</correlation>
        <correlation entry="d15d21">0</correlation>
        <correlation entry="d15d22">0</correlation>
        <correlation entry="d15d23">0</correlation>
        <correlation entry="d15d24">0</correlation>
        <correlation entry="d15d25">0</correlation>
        <correlation entry="d15d26">0</correlation>
        <correlation entry="d15d27">0.01</correlation>
        <correlation entry="d15d28">-0.05</correlation>                         
        <correlation entry="d15d29">0</correlation>
        <correlation entry="d15d30">0</correlation>
        
        <correlation entry="d16d17">-0.31</correlation>
        <correlation entry="d16d18">-0.16</correlation>
        <correlation entry="d16d19">-0.09</correlation>
        <correlation entry="d16d20">-0.01</correlation>
        <correlation entry="d16d21">0</correlation>
        <correlation entry="d16d22">0</correlation>
        <correlation entry="d16d23">0</correlation>
        <correlation entry="d16d24">0</correlation>
        <correlation entry="d16d25">0</correlation>
        <correlation entry="d16d26">0</correlation>
        <correlation entry="d16d27">0</correlation>
        <correlation entry="d16d28">0</correlation>        
        <correlation entry="d16d29">0.03</correlation>
        <correlation entry="d16d30">0</correlation>
        
        <correlation entry="d17d18">0.03</correlation>
        <correlation entry="d17d19">0.03</correlation>
        <correlation entry="d17d20">0.01</correlation>
        <correlation entry="d17d21">0</correlation>
        <correlation entry="d17d22">0.01</correlation>
        <correlation entry="d17d23">0</correlation>
        <correlation entry="d17d24">0</correlation>
        <correlation entry="d17d25">0</correlation>
        <correlation entry="d17d26">0.01</correlation>
        <correlation entry="d17d27">0.01</correlation>
        <correlation entry="d17d28">0</correlation>                
        <correlation entry="d17d29">0</correlation>
        <correlation entry="d17d30">-0.01</correlation>
        
        <correlation entry="d18d19">-0.02</correlation>
        <correlation entry="d18d20">0</correlation>
        <correlation entry="d18d21">0</correlation>
        <correlation entry="d18d22">0</correlation>
        <correlation entry="d18d23">0</correlation>
        <correlation entry="d18d24">0</correlation>
        <correlation entry="d18d25">0</correlation>
        <correlation entry="d18d26">0</correlation>
        <correlation entry="d18d27">0</correlation>
        <correlation entry="d18d28">0</correlation>        
        <correlation entry="d18d29">0</correlation>
        <correlation entry="d18d30">0</correlation>
        
        <correlation entry="d19d20">0</correlation>
        <correlation entry="d19d21">0</correlation>
        <correlation entry="d19d22">0</correlation>
        <correlation entry="d19d23">0.02</correlation>
        <correlation entry="d19d24">0</correlation>
        <correlation entry="d19d25">0</correlation>
        <correlation entry="d19d26">0.01</correlation>
        <correlation entry="d19d27">0</correlation>
        <correlation entry="d19d28">0</correlation>      
        <correlation entry="d19d29">0.01</correlation>
        <correlation entry="d19d30">0</correlation>
        
        <correlation entry="d20d21">0</correlation>
        <correlation entry="d20d22">0</correlation>
        <correlation entry="d20d23">0</correlation>
        <correlation entry="d20d24">0.03</correlation>
        <correlation entry="d20d25">0</correlation>
        <correlation entry="d20d26">0</correlation>
        <correlation entry="d20d27">0</correlation>
        <correlation entry="d20d28">0.03</correlation>
        <correlation entry="d20d29">0</correlation>
        <correlation entry="d20d30">0</correlation>
        
        <correlation entry="d21d22">-0.02</correlation>
        <correlation entry="d21d23">-0.01</correlation>
        <correlation entry="d21d24">0</correlation>
        <correlation entry="d21d25">0</correlation>
        <correlation entry="d21d26">0</correlation>
        <correlation entry="d21d27">0</correlation>
        <correlation entry="d21d28">0</correlation>        
        <correlation entry="d21d29">0</correlation>
        <correlation entry="d21d30">0</correlation>
        
        <correlation entry="d22d23">-0.04</correlation>
        <correlation entry="d22d24">0</correlation>
        <correlation entry="d22d25">0</correlation>
        <correlation entry="d22d26">0</correlation>
        <correlation entry="d22d27">0</correlation>
        <correlation entry="d22d28">0</correlation>        	
        <correlation entry="d22d29">0</correlation>
        <correlation entry="d22d30">0</correlation>
        
        <correlation entry="d23d24">0</correlation>
        <correlation entry="d23d25">0</correlation>
        <correlation entry="d23d26">0</correlation>
        <correlation entry="d23d27">0</correlation>
        <correlation entry="d23d28">0</correlation>   
        <correlation entry="d23d29">0</correlation>
        <correlation entry="d23d30">0</correlation>
        
        <correlation entry="d24d25">0</correlation>
        <correlation entry="d24d26">0</correlation>
        <correlation entry="d24d27">0</correlation>
        <correlation entry="d24d28">0.03</correlation>
        <correlation entry="d24d29">0</correlation>
        <correlation entry="d24d30">0</correlation>
        
        <correlation entry="d25d26">-0.23</correlation>
        <correlation entry="d25d27">-0.12</correlation>
        <correlation entry="d25d28">0.01</correlation>
        <correlation entry="d25d29">-0.01</correlation>
        <correlation entry="d25d30">0</correlation>
        
        <correlation entry="d26d27">0.02</correlation>
        <correlation entry="d26d28">0</correlation>                
        <correlation entry="d26d29">0</correlation>
        <correlation entry="d26d30">-0.01</correlation>
        
        <correlation entry="d27d28">-0.08</correlation>   
        <correlation entry="d27d29">0</correlation>
        <correlation entry="d27d30">0</correlation>
        
        <correlation entry="d28d29">0</correlation>        
        <correlation entry="d28d30">0</correlation>       
                 
        <correlation entry="d29d30">-0.4</correlation>
    </param>
</expmu>
